{
  "version": "3.2",
  "log": [
    {
      "Greeter": {
        "src": "contracts\\Greeter.sol:6",
        "version": {
          "withMetadata": "0d4fcb95cdd3a6aefea8a9d8475ee55e1ea478205ad06a4b3f632a24226c9ce1",
          "withoutMetadata": "0d4fcb95cdd3a6aefea8a9d8475ee55e1ea478205ad06a4b3f632a24226c9ce1",
          "linkedWithoutMetadata": "0d4fcb95cdd3a6aefea8a9d8475ee55e1ea478205ad06a4b3f632a24226c9ce1"
        },
        "inherit": [],
        "libraries": [
          "console"
        ],
        "methods": [
          "(string)",
          "greet()",
          "setGreeting(string)"
        ],
        "linkReferences": [],
        "errors": [
          {
            "kind": "constructor",
            "contract": "Greeter",
            "src": "contracts\\Greeter.sol:9"
          }
        ],
        "layout": {
          "storage": [
            {
              "contract": "Greeter",
              "label": "greeting",
              "type": "t_string_storage",
              "src": "contracts\\Greeter.sol:7"
            }
          ],
          "types": {
            "t_string_storage": {
              "label": "string"
            }
          },
          "layoutVersion": "1.1"
        }
      },
      "SimpleStorageUpgrade": {
        "src": "contracts\\SimpleStorageUpgrade.sol:5",
        "version": {
          "withMetadata": "377f012e5183fb4774c85d13b78c2a7e890cbd2812170a4ba16c5bb87d6be486",
          "withoutMetadata": "1178900bded31ff356a777efb9b6b512eb8f215385367633a5b28268926bd667",
          "linkedWithoutMetadata": "1178900bded31ff356a777efb9b6b512eb8f215385367633a5b28268926bd667"
        },
        "inherit": [],
        "libraries": [],
        "methods": [
          "set(uint256)",
          "get()"
        ],
        "linkReferences": [],
        "errors": [],
        "layout": {
          "storage": [
            {
              "contract": "SimpleStorageUpgrade",
              "label": "storedData",
              "type": "t_uint256",
              "src": "contracts\\SimpleStorageUpgrade.sol:6"
            }
          ],
          "types": {
            "t_uint256": {
              "label": "uint256"
            }
          },
          "layoutVersion": "1.1"
        }
      },
      "console": {
        "src": "hardhat\\console.sol:4",
        "version": {
          "withMetadata": "beae05454d6c24b0af2926d3f12cbd62c3db4a4f7dff423bd7ff2ddbe2972f20",
          "withoutMetadata": "08d24783a787f8a51dea0c166bb6f91a4f0865e02d03d749f102d332e6ead0ff",
          "linkedWithoutMetadata": "08d24783a787f8a51dea0c166bb6f91a4f0865e02d03d749f102d332e6ead0ff"
        },
        "inherit": [],
        "libraries": [],
        "methods": [],
        "linkReferences": [],
        "errors": [],
        "layout": {
          "storage": [],
          "types": {},
          "layoutVersion": "1.1"
        }
      }
    }
  ]
}